{
  "match_id": 5235266369,
  "barracks_status_dire": 51,
  "barracks_status_radiant": 63,
  "chat": null,
  "cluster": 111,
  "cosmetics": null,
  "dire_score": 5,
  "dire_team_id": null,
  "draft_timings": null,
  "duration": 1075,
  "engine": 1,
  "first_blood_time": 166,
  "game_mode": 3,
  "human_players": 10,
  "leagueid": 0,
  "lobby_type": 0,
  "match_seq_num": 4392867968,
  "negative_votes": 0,
  "objectives": null,
  "picks_bans": null,
  "positive_votes": 0,
  "radiant_gold_adv": null,
  "radiant_score": 27,
  "radiant_team_id": null,
  "radiant_win": true,
  "radiant_xp_adv": null,
  "skill": 1,
  "start_time": 1581281452,
  "teamfights": null,
  "tower_status_dire": 452,
  "tower_status_radiant": 2047,
  "version": null,
  "replay_salt": 959292558,
  "series_id": 0,
  "series_type": 0,
  "players": [
    {
      "match_id": 5235266369,
      "player_slot": 0,
      "ability_targets": null,
      "ability_upgrades_arr": [],
      "ability_uses": null,
      "account_id": 36541532,
      "actions": null,
      "additional_units": null,
      "assists": 2,
      "backpack_0": 16,
      "backpack_1": 16,
      "backpack_2": 44,
      "backpack_3": null,
      "buyback_log": null,
      "camps_stacked": null,
      "connection_log": null,
      "creeps_stacked": null,
      "damage": null,
      "damage_inflictor": null,
      "damage_inflictor_received": null,
      "damage_taken": null,
      "damage_targets": null,
      "deaths": 2,
      "denies": 38,
      "dn_t": null,
      "firstblood_claimed": null,
      "gold": 2008,
      "gold_per_min": 511,
      "gold_reasons": null,
      "gold_spent": 7960,
      "gold_t": null,
      "hero_damage": 5818,
      "hero_healing": 0,
      "hero_hits": null,
      "hero_id": 59,
      "item_0": 162,
      "item_1": 151,
      "item_2": 63,
      "item_3": 26,
      "item_4": 244,
      "item_5": 40,
      "item_uses": null,
      "kill_streaks": null,
      "killed": null,
      "killed_by": null,
      "kills": 5,
      "kills_log": null,
      "lane_pos": null,
      "last_hits": 90,
      "leaver_status": 0,
      "level": 13,
      "lh_t": null,
      "life_state": null,
      "max_hero_hit": null,
      "multi_kills": null,
      "obs": null,
      "obs_left_log": null,
      "obs_log": null,
      "obs_placed": null,
      "party_id": 0,
      "party_size": 1,
      "performance_others": null,
      "permanent_buffs": null,
      "pings": null,
      "pred_vict": null,
      "purchase": null,
      "purchase_log": null,
      "randomed": null,
      "repicked": null,
      "roshans_killed": null,
      "rune_pickups": null,
      "runes": null,
      "runes_log": null,
      "sen": null,
      "sen_left_log": null,
      "sen_log": null,
      "sen_placed": null,
      "stuns": null,
      "teamfight_participation": null,
      "times": null,
      "tower_damage": 6354,
      "towers_killed": null,
      "xp_per_min": 476,
      "xp_reasons": null,
      "xp_t": null,
      "personaname": "non-offensive online name",
      "name": null,
      "last_login": "2018-09-20T05:21:09.498Z",
      "radiant_win": true,
      "start_time": 1581281452,
      "duration": 1075,
      "cluster": 111,
      "lobby_type": 0,
      "game_mode": 3,
      "is_contributor": false,
      "patch": 43,
      "region": 1,
      "isRadiant": true,
      "win": 1,
      "lose": 0,
      "total_gold": 9155,
      "total_xp": 8528,
      "kills_per_min": 0.27906976744186046,
      "kda": 2,
      "abandons": 0,
      "rank_tier": 55,
      "cosmetics": [],
      "benchmarks": []
    },
    {
      "match_id": 5235266369,
      "player_slot": 1,
      "ability_targets": null,
      "ability_upgrades_arr": [],
      "ability_uses": null,
      "account_id": 677050,
      "actions": null,
      "additional_units": null,
      "assists": 7,
      "backpack_0": 0,
      "backpack_1": 0,
      "backpack_2": 0,
      "backpack_3": null,
      "buyback_log": null,
      "camps_stacked": null,
      "connection_log": null,
      "creeps_stacked": null,
      "damage": null,
      "damage_inflictor": null,
      "damage_inflictor_received": null,
      "damage_taken": null,
      "damage_targets": null,
      "deaths": 2,
      "denies": 5,
      "dn_t": null,
      "firstblood_claimed": null,
      "gold": 476,
      "gold_per_min": 391,
      "gold_reasons": null,
      "gold_spent": 7005,
      "gold_t": null,
      "hero_damage": 7916,
      "hero_healing": 0,
      "hero_hits": null,
      "hero_id": 13,
      "item_0": 1,
      "item_1": 240,
      "item_2": 36,
      "item_3": 63,
      "item_4": 77,
      "item_5": 8,
      "item_uses": null,
      "kill_streaks": null,
      "killed": null,
      "killed_by": null,
      "kills": 5,
      "kills_log": null,
      "lane_pos": null,
      "last_hits": 61,
      "leaver_status": 0,
      "level": 10,
      "lh_t": null,
      "life_state": null,
      "max_hero_hit": null,
      "multi_kills": null,
      "obs": null,
      "obs_left_log": null,
      "obs_log": null,
      "obs_placed": null,
      "party_id": 1,
      "party_size": 2,
      "performance_others": null,
      "permanent_buffs": [],
      "pings": null,
      "pred_vict": null,
      "purchase": null,
      "purchase_log": null,
      "randomed": null,
      "repicked": null,
      "roshans_killed": null,
      "rune_pickups": null,
      "runes": null,
      "runes_log": null,
      "sen": null,
      "sen_left_log": null,
      "sen_log": null,
      "sen_placed": null,
      "stuns": null,
      "teamfight_participation": null,
      "times": null,
      "tower_damage": 1029,
      "towers_killed": null,
      "xp_per_min": 300,
      "xp_reasons": null,
      "xp_t": null,
      "personaname": "PHLAK",
      "name": null,
      "last_login": null,
      "radiant_win": true,
      "start_time": 1581281452,
      "duration": 1075,
      "cluster": 111,
      "lobby_type": 0,
      "game_mode": 3,
      "is_contributor": false,
      "patch": 43,
      "region": 1,
      "isRadiant": true,
      "win": 1,
      "lose": 0,
      "total_gold": 7005,
      "total_xp": 5375,
      "kills_per_min": 0.27906976744186046,
      "kda": 4,
      "abandons": 0,
      "rank_tier": null,
      "cosmetics": [],
      "benchmarks": []
    },
    {
      "match_id": 5235266369,
      "player_slot": 2,
      "ability_targets": null,
      "ability_upgrades_arr": [],
      "ability_uses": null,
      "account_id": 11707256,
      "actions": null,
      "additional_units": null,
      "assists": 8,
      "backpack_0": 16,
      "backpack_1": 0,
      "backpack_2": 0,
      "backpack_3": null,
      "buyback_log": null,
      "camps_stacked": null,
      "connection_log": null,
      "creeps_stacked": null,
      "damage": null,
      "damage_inflictor": null,
      "damage_inflictor_received": null,
      "damage_taken": null,
      "damage_targets": null,
      "deaths": 0,
      "denies": 15,
      "dn_t": null,
      "firstblood_claimed": null,
      "gold": 1341,
      "gold_per_min": 414,
      "gold_reasons": null,
      "gold_spent": 6695,
      "gold_t": null,
      "hero_damage": 4967,
      "hero_healing": 0,
      "hero_hits": null,
      "hero_id": 28,
      "item_0": 216,
      "item_1": 252,
      "item_2": 11,
      "item_3": 1,
      "item_4": 16,
      "item_5": 63,
      "item_uses": null,
      "kill_streaks": null,
      "killed": null,
      "killed_by": null,
      "kills": 3,
      "kills_log": null,
      "lane_pos": null,
      "last_hits": 67,
      "leaver_status": 0,
      "level": 11,
      "lh_t": null,
      "life_state": null,
      "max_hero_hit": null,
      "multi_kills": null,
      "obs": null,
      "obs_left_log": null,
      "obs_log": null,
      "obs_placed": null,
      "party_id": 1,
      "party_size": 2,
      "performance_others": null,
      "permanent_buffs": null,
      "pings": null,
      "pred_vict": null,
      "purchase": null,
      "purchase_log": null,
      "randomed": null,
      "repicked": null,
      "roshans_killed": null,
      "rune_pickups": null,
      "runes": null,
      "runes_log": null,
      "sen": null,
      "sen_left_log": null,
      "sen_log": null,
      "sen_placed": null,
      "stuns": null,
      "teamfight_participation": null,
      "times": null,
      "tower_damage": 1555,
      "towers_killed": null,
      "xp_per_min": 362,
      "xp_reasons": null,
      "xp_t": null,
      "personaname": "static",
      "name": null,
      "last_login": null,
      "radiant_win": true,
      "start_time": 1581281452,
      "duration": 1075,
      "cluster": 111,
      "lobby_type": 0,
      "game_mode": 3,
      "is_contributor": false,
      "patch": 43,
      "region": 1,
      "isRadiant": true,
      "win": 1,
      "lose": 0,
      "total_gold": 7417,
      "total_xp": 6485,
      "kills_per_min": 0.16744186046511628,
      "kda": 11,
      "abandons": 0,
      "rank_tier": null,
      "cosmetics": [],
      "benchmarks": []
    },
    {
      "match_id": 5235266369,
      "player_slot": 3,
      "ability_targets": null,
      "ability_upgrades_arr": [],
      "ability_uses": null,
      "account_id": 64765188,
      "actions": null,
      "additional_units": null,
      "assists": 8,
      "backpack_0": 40,
      "backpack_1": 34,
      "backpack_2": 0,
      "backpack_3": null,
      "buyback_log": null,
      "camps_stacked": null,
      "connection_log": null,
      "creeps_stacked": null,
      "damage": null,
      "damage_inflictor": null,
      "damage_inflictor_received": null,
      "damage_taken": null,
      "damage_targets": null,
      "deaths": 1,
      "denies": 1,
      "dn_t": null,
      "firstblood_claimed": null,
      "gold": 540,
      "gold_per_min": 343,
      "gold_reasons": null,
      "gold_spent": 6205,
      "gold_t": null,
      "hero_damage": 11706,
      "hero_healing": 0,
      "hero_hits": null,
      "hero_id": 31,
      "item_0": 88,
      "item_1": 214,
      "item_2": 232,
      "item_3": 38,
      "item_4": 37,
      "item_5": 43,
      "item_uses": null,
      "kill_streaks": null,
      "killed": null,
      "killed_by": null,
      "kills": 7,
      "kills_log": null,
      "lane_pos": null,
      "last_hits": 10,
      "leaver_status": 0,
      "level": 9,
      "lh_t": null,
      "life_state": null,
      "max_hero_hit": null,
      "multi_kills": null,
      "obs": null,
      "obs_left_log": null,
      "obs_log": null,
      "obs_placed": null,
      "party_id": 2,
      "party_size": 2,
      "performance_others": null,
      "permanent_buffs": null,
      "pings": null,
      "pred_vict": null,
      "purchase": null,
      "purchase_log": null,
      "randomed": null,
      "repicked": null,
      "roshans_killed": null,
      "rune_pickups": null,
      "runes": null,
      "runes_log": null,
      "sen": null,
      "sen_left_log": null,
      "sen_log": null,
      "sen_placed": null,
      "stuns": null,
      "teamfight_participation": null,
      "times": null,
      "tower_damage": 1026,
      "towers_killed": null,
      "xp_per_min": 264,
      "xp_reasons": null,
      "xp_t": null,
      "personaname": "Furikz",
      "name": null,
      "last_login": "2020-02-09T21:30:16.631Z",
      "radiant_win": true,
      "start_time": 1581281452,
      "duration": 1075,
      "cluster": 111,
      "lobby_type": 0,
      "game_mode": 3,
      "is_contributor": false,
      "patch": 43,
      "region": 1,
      "isRadiant": true,
      "win": 1,
      "lose": 0,
      "total_gold": 6145,
      "total_xp": 4730,
      "kills_per_min": 0.39069767441860465,
      "kda": 7,
      "abandons": 0,
      "rank_tier": 63,
      "cosmetics": [],
      "benchmarks": []
    },
    {
      "match_id": 5235266369,
      "player_slot": 4,
      "ability_targets": null,
      "ability_upgrades_arr": [],
      "ability_uses": null,
      "account_id": 37768448,
      "actions": null,
      "additional_units": null,
      "assists": 3,
      "backpack_0": 216,
      "backpack_1": 0,
      "backpack_2": 11,
      "backpack_3": null,
      "buyback_log": null,
      "camps_stacked": null,
      "connection_log": null,
      "creeps_stacked": null,
      "damage": null,
      "damage_inflictor": null,
      "damage_inflictor_received": null,
      "damage_taken": null,
      "damage_targets": null,
      "deaths": 0,
      "denies": 44,
      "dn_t": null,
      "firstblood_claimed": null,
      "gold": 1898,
      "gold_per_min": 560,
      "gold_reasons": null,
      "gold_spent": 8885,
      "gold_t": null,
      "hero_damage": 8284,
      "hero_healing": 0,
      "hero_hits": null,
      "hero_id": 32,
      "item_0": 75,
      "item_1": 50,
      "item_2": 174,
      "item_3": 36,
      "item_4": 75,
      "item_5": 24,
      "item_uses": null,
      "kill_streaks": null,
      "killed": null,
      "killed_by": null,
      "kills": 7,
      "kills_log": null,
      "lane_pos": null,
      "last_hits": 111,
      "leaver_status": 0,
      "level": 13,
      "lh_t": null,
      "life_state": null,
      "max_hero_hit": null,
      "multi_kills": null,
      "obs": null,
      "obs_left_log": null,
      "obs_log": null,
      "obs_placed": null,
      "party_id": 2,
      "party_size": 2,
      "performance_others": null,
      "permanent_buffs": null,
      "pings": null,
      "pred_vict": null,
      "purchase": null,
      "purchase_log": null,
      "randomed": null,
      "repicked": null,
      "roshans_killed": null,
      "rune_pickups": null,
      "runes": null,
      "runes_log": null,
      "sen": null,
      "sen_left_log": null,
      "sen_log": null,
      "sen_placed": null,
      "stuns": null,
      "teamfight_participation": null,
      "times": null,
      "tower_damage": 1483,
      "towers_killed": null,
      "xp_per_min": 504,
      "xp_reasons": null,
      "xp_t": null,
      "personaname": "SupahNoob",
      "name": null,
      "last_login": "2019-08-23T00:27:49.921Z",
      "radiant_win": true,
      "start_time": 1581281452,
      "duration": 1075,
      "cluster": 111,
      "lobby_type": 0,
      "game_mode": 3,
      "is_contributor": false,
      "patch": 43,
      "region": 1,
      "isRadiant": true,
      "win": 1,
      "lose": 0,
      "total_gold": 10033,
      "total_xp": 9030,
      "kills_per_min": 0.39069767441860465,
      "kda": 10,
      "abandons": 0,
      "rank_tier": 61,
      "cosmetics": [],
      "benchmarks": []
    },
    {
      "match_id": 5235266369,
      "player_slot": 128,
      "ability_targets": null,
      "ability_upgrades_arr": [],
      "ability_uses": null,
      "account_id": null,
      "actions": null,
      "additional_units": null,
      "assists": 0,
      "backpack_0": 38,
      "backpack_1": 0,
      "backpack_2": 0,
      "backpack_3": null,
      "buyback_log": null,
      "camps_stacked": null,
      "connection_log": null,
      "creeps_stacked": null,
      "damage": null,
      "damage_inflictor": null,
      "damage_inflictor_received": null,
      "damage_taken": null,
      "damage_targets": null,
      "deaths": 7,
      "denies": 3,
      "dn_t": null,
      "firstblood_claimed": null,
      "gold": 1,
      "gold_per_min": 190,
      "gold_reasons": null,
      "gold_spent": 3045,
      "gold_t": null,
      "hero_damage": 3364,
      "hero_healing": 0,
      "hero_hits": null,
      "hero_id": 74,
      "item_0": 65,
      "item_1": 39,
      "item_2": 20,
      "item_3": 237,
      "item_4": 216,
      "item_5": 15,
      "item_uses": null,
      "kill_streaks": null,
      "killed": null,
      "killed_by": null,
      "kills": 2,
      "kills_log": null,
      "lane_pos": null,
      "last_hits": 15,
      "leaver_status": 1,
      "level": 9,
      "lh_t": null,
      "life_state": null,
      "max_hero_hit": null,
      "multi_kills": null,
      "obs": null,
      "obs_left_log": null,
      "obs_log": null,
      "obs_placed": null,
      "party_id": 3,
      "party_size": 5,
      "performance_others": null,
      "permanent_buffs": null,
      "pings": null,
      "pred_vict": null,
      "purchase": null,
      "purchase_log": null,
      "randomed": null,
      "repicked": null,
      "roshans_killed": null,
      "rune_pickups": null,
      "runes": null,
      "runes_log": null,
      "sen": null,
      "sen_left_log": null,
      "sen_log": null,
      "sen_placed": null,
      "stuns": null,
      "teamfight_participation": null,
      "times": null,
      "tower_damage": 0,
      "towers_killed": null,
      "xp_per_min": 278,
      "xp_reasons": null,
      "xp_t": null,
      "radiant_win": true,
      "start_time": 1581281452,
      "duration": 1075,
      "cluster": 111,
      "lobby_type": 0,
      "game_mode": 3,
      "is_contributor": false,
      "patch": 43,
      "region": 1,
      "isRadiant": false,
      "win": 0,
      "lose": 1,
      "total_gold": 3404,
      "total_xp": 4980,
      "kills_per_min": 0.11162790697674418,
      "kda": 0,
      "abandons": 0,
      "rank_tier": null,
      "cosmetics": [],
      "benchmarks": []
    },
    {
      "match_id": 5235266369,
      "player_slot": 129,
      "ability_targets": null,
      "ability_upgrades_arr": [],
      "ability_uses": null,
      "account_id": null,
      "actions": null,
      "additional_units": null,
      "assists": 0,
      "backpack_0": 25,
      "backpack_1": 0,
      "backpack_2": 0,
      "backpack_3": null,
      "buyback_log": null,
      "camps_stacked": null,
      "connection_log": null,
      "creeps_stacked": null,
      "damage": null,
      "damage_inflictor": null,
      "damage_inflictor_received": null,
      "damage_taken": null,
      "damage_targets": null,
      "deaths": 5,
      "denies": 3,
      "dn_t": null,
      "firstblood_claimed": null,
      "gold": 1530,
      "gold_per_min": 217,
      "gold_reasons": null,
      "gold_spent": 2760,
      "gold_t": null,
      "hero_damage": 4199,
      "hero_healing": 0,
      "hero_hits": null,
      "hero_id": 99,
      "item_0": 40,
      "item_1": 216,
      "item_2": 218,
      "item_3": 181,
      "item_4": 29,
      "item_5": 88,
      "item_uses": null,
      "kill_streaks": null,
      "killed": null,
      "killed_by": null,
      "kills": 1,
      "kills_log": null,
      "lane_pos": null,
      "last_hits": 18,
      "leaver_status": 1,
      "level": 8,
      "lh_t": null,
      "life_state": null,
      "max_hero_hit": null,
      "multi_kills": null,
      "obs": null,
      "obs_left_log": null,
      "obs_log": null,
      "obs_placed": null,
      "party_id": 3,
      "party_size": 5,
      "performance_others": null,
      "permanent_buffs": [],
      "pings": null,
      "pred_vict": null,
      "purchase": null,
      "purchase_log": null,
      "randomed": null,
      "repicked": null,
      "roshans_killed": null,
      "rune_pickups": null,
      "runes": null,
      "runes_log": null,
      "sen": null,
      "sen_left_log": null,
      "sen_log": null,
      "sen_placed": null,
      "stuns": null,
      "teamfight_participation": null,
      "times": null,
      "tower_damage": 0,
      "towers_killed": null,
      "xp_per_min": 223,
      "xp_reasons": null,
      "xp_t": null,
      "radiant_win": true,
      "start_time": 1581281452,
      "duration": 1075,
      "cluster": 111,
      "lobby_type": 0,
      "game_mode": 3,
      "is_contributor": false,
      "patch": 43,
      "region": 1,
      "isRadiant": false,
      "win": 0,
      "lose": 1,
      "total_gold": 3887,
      "total_xp": 3995,
      "kills_per_min": 0.05581395348837209,
      "kda": 0,
      "abandons": 0,
      "rank_tier": null,
      "cosmetics": [],
      "benchmarks": []
    },
    {
      "match_id": 5235266369,
      "player_slot": 130,
      "ability_targets": null,
      "ability_upgrades_arr": [],
      "ability_uses": null,
      "account_id": null,
      "actions": null,
      "additional_units": null,
      "assists": 0,
      "backpack_0": 304,
      "backpack_1": 0,
      "backpack_2": 0,
      "backpack_3": null,
      "buyback_log": null,
      "camps_stacked": null,
      "connection_log": null,
      "creeps_stacked": null,
      "damage": null,
      "damage_inflictor": null,
      "damage_inflictor_received": null,
      "damage_taken": null,
      "damage_targets": null,
      "deaths": 9,
      "denies": 0,
      "dn_t": null,
      "firstblood_claimed": null,
      "gold": 2,
      "gold_per_min": 144,
      "gold_reasons": null,
      "gold_spent": 2380,
      "gold_t": null,
      "hero_damage": 2474,
      "hero_healing": 0,
      "hero_hits": null,
      "hero_id": 108,
      "item_0": 178,
      "item_1": 16,
      "item_2": 16,
      "item_3": 29,
      "item_4": 216,
      "item_5": 11,
      "item_uses": null,
      "kill_streaks": null,
      "killed": null,
      "killed_by": null,
      "kills": 0,
      "kills_log": null,
      "lane_pos": null,
      "last_hits": 25,
      "leaver_status": 3,
      "level": 6,
      "lh_t": null,
      "life_state": null,
      "max_hero_hit": null,
      "multi_kills": null,
      "obs": null,
      "obs_left_log": null,
      "obs_log": null,
      "obs_placed": null,
      "party_id": 3,
      "party_size": 5,
      "performance_others": null,
      "permanent_buffs": [],
      "pings": null,
      "pred_vict": null,
      "purchase": null,
      "purchase_log": null,
      "randomed": null,
      "repicked": null,
      "roshans_killed": null,
      "rune_pickups": null,
      "runes": null,
      "runes_log": null,
      "sen": null,
      "sen_left_log": null,
      "sen_log": null,
      "sen_placed": null,
      "stuns": null,
      "teamfight_participation": null,
      "times": null,
      "tower_damage": 0,
      "towers_killed": null,
      "xp_per_min": 127,
      "xp_reasons": null,
      "xp_t": null,
      "radiant_win": true,
      "start_time": 1581281452,
      "duration": 1075,
      "cluster": 111,
      "lobby_type": 0,
      "game_mode": 3,
      "is_contributor": false,
      "patch": 43,
      "region": 1,
      "isRadiant": false,
      "win": 0,
      "lose": 1,
      "total_gold": 2580,
      "total_xp": 2275,
      "kda": 0,
      "abandons": 1,
      "rank_tier": null,
      "cosmetics": [],
      "benchmarks": []
    },
    {
      "match_id": 5235266369,
      "player_slot": 131,
      "ability_targets": null,
      "ability_upgrades_arr": [],
      "ability_uses": null,
      "account_id": null,
      "actions": null,
      "additional_units": null,
      "assists": 1,
      "backpack_0": 0,
      "backpack_1": 0,
      "backpack_2": 0,
      "backpack_3": null,
      "buyback_log": null,
      "camps_stacked": null,
      "connection_log": null,
      "creeps_stacked": null,
      "damage": null,
      "damage_inflictor": null,
      "damage_inflictor_received": null,
      "damage_taken": null,
      "damage_targets": null,
      "deaths": 4,
      "denies": 2,
      "dn_t": null,
      "firstblood_claimed": null,
      "gold": 2,
      "gold_per_min": 147,
      "gold_reasons": null,
      "gold_spent": 2150,
      "gold_t": null,
      "hero_damage": 3416,
      "hero_healing": 0,
      "hero_hits": null,
      "hero_id": 6,
      "item_0": 63,
      "item_1": 36,
      "item_2": 44,
      "item_3": 38,
      "item_4": 0,
      "item_5": 0,
      "item_uses": null,
      "kill_streaks": null,
      "killed": null,
      "killed_by": null,
      "kills": 0,
      "kills_log": null,
      "lane_pos": null,
      "last_hits": 15,
      "leaver_status": 1,
      "level": 7,
      "lh_t": null,
      "life_state": null,
      "max_hero_hit": null,
      "multi_kills": null,
      "obs": null,
      "obs_left_log": null,
      "obs_log": null,
      "obs_placed": null,
      "party_id": 3,
      "party_size": 5,
      "performance_others": null,
      "permanent_buffs": null,
      "pings": null,
      "pred_vict": null,
      "purchase": null,
      "purchase_log": null,
      "randomed": null,
      "repicked": null,
      "roshans_killed": null,
      "rune_pickups": null,
      "runes": null,
      "runes_log": null,
      "sen": null,
      "sen_left_log": null,
      "sen_log": null,
      "sen_placed": null,
      "stuns": null,
      "teamfight_participation": null,
      "times": null,
      "tower_damage": 0,
      "towers_killed": null,
      "xp_per_min": 198,
      "xp_reasons": null,
      "xp_t": null,
      "radiant_win": true,
      "start_time": 1581281452,
      "duration": 1075,
      "cluster": 111,
      "lobby_type": 0,
      "game_mode": 3,
      "is_contributor": false,
      "patch": 43,
      "region": 1,
      "isRadiant": false,
      "win": 0,
      "lose": 1,
      "total_gold": 2633,
      "total_xp": 3547,
      "kda": 0,
      "abandons": 0,
      "rank_tier": null,
      "cosmetics": [],
      "benchmarks": []
    },
    {
      "match_id": 5235266369,
      "player_slot": 132,
      "ability_targets": null,
      "ability_upgrades_arr": [],
      "ability_uses": null,
      "account_id": 111747696,
      "actions": null,
      "additional_units": null,
      "assists": 0,
      "backpack_0": 0,
      "backpack_1": 0,
      "backpack_2": 0,
      "backpack_3": null,
      "buyback_log": null,
      "camps_stacked": null,
      "connection_log": null,
      "creeps_stacked": null,
      "damage": null,
      "damage_inflictor": null,
      "damage_inflictor_received": null,
      "damage_taken": null,
      "damage_targets": null,
      "deaths": 2,
      "denies": 11,
      "dn_t": null,
      "firstblood_claimed": null,
      "gold": 1463,
      "gold_per_min": 195,
      "gold_reasons": null,
      "gold_spent": 2690,
      "gold_t": null,
      "hero_damage": 3095,
      "hero_healing": 120,
      "hero_hits": null,
      "hero_id": 102,
      "item_0": 214,
      "item_1": 36,
      "item_2": 216,
      "item_3": 88,
      "item_4": 43,
      "item_5": 0,
      "item_uses": null,
      "kill_streaks": null,
      "killed": null,
      "killed_by": null,
      "kills": 0,
      "kills_log": null,
      "lane_pos": null,
      "last_hits": 18,
      "leaver_status": 1,
      "level": 7,
      "lh_t": null,
      "life_state": null,
      "max_hero_hit": null,
      "multi_kills": null,
      "obs": null,
      "obs_left_log": null,
      "obs_log": null,
      "obs_placed": null,
      "party_id": 3,
      "party_size": 5,
      "performance_others": null,
      "permanent_buffs": null,
      "pings": null,
      "pred_vict": null,
      "purchase": null,
      "purchase_log": null,
      "randomed": null,
      "repicked": null,
      "roshans_killed": null,
      "rune_pickups": null,
      "runes": null,
      "runes_log": null,
      "sen": null,
      "sen_left_log": null,
      "sen_log": null,
      "sen_placed": null,
      "stuns": null,
      "teamfight_participation": null,
      "times": null,
      "tower_damage": 0,
      "towers_killed": null,
      "xp_per_min": 200,
      "xp_reasons": null,
      "xp_t": null,
      "personaname": "Maliblue",
      "name": null,
      "last_login": null,
      "radiant_win": true,
      "start_time": 1581281452,
      "duration": 1075,
      "cluster": 111,
      "lobby_type": 0,
      "game_mode": 3,
      "is_contributor": false,
      "patch": 43,
      "region": 1,
      "isRadiant": false,
      "win": 0,
      "lose": 1,
      "total_gold": 3493,
      "total_xp": 3583,
      "kda": 0,
      "abandons": 0,
      "rank_tier": 72,
      "cosmetics": [],
      "benchmarks": []
    }
  ],
  "patch": 43,
  "region": 1,
  "replay_url": "http://replay111.valve.net/570/5235266369_959292558.dem.bz2"
}
